roundtripper/__init__.py
roundtripper/api_client.py
roundtripper/cli.py
roundtripper/config.py
roundtripper/config_interactive.py
roundtripper/config_store.py
roundtripper/confluence.py
roundtripper/file_utils.py
roundtripper/models.py
roundtripper/pull_service.py
roundtripper/push_service.py
roundtripper/py.typed
roundtripper-0.2.0.dist-info/METADATA
roundtripper-0.2.0.dist-info/WHEEL
roundtripper-0.2.0.dist-info/entry_points.txt
roundtripper-0.2.0.dist-info/licenses/LICENSE
roundtripper-0.2.0.dist-info/RECORD
