Metadata-Version: 2.4
Name: roundtripper
Version: 0.2.0
Summary: Roundtripping with Confluence
Project-URL: Documentation, https://github.com/holtgrewe/roundtripper
Project-URL: Issues, https://github.com/holtgrewe/roundtripper/issues
Project-URL: Source, https://github.com/holtgrewe/roundtripper
License-File: LICENSE
Requires-Python: >=3.13
Requires-Dist: atlassian-python-api>=3.41.0
Requires-Dist: cyclopts>=4.4.4
Requires-Dist: httpx>=0.28.1
Requires-Dist: jmespath>=1.0.1
Requires-Dist: pydantic-settings>=2.7.0
Requires-Dist: pydantic>=2.10.6
Requires-Dist: questionary>=2.0.1
Requires-Dist: rich>=13.9.4
Requires-Dist: tqdm>=4.66.0
